metalogger/__init__.py
metalogger-1.0.1.dist-info/METADATA
metalogger-1.0.1.dist-info/WHEEL
metalogger-1.0.1.dist-info/top_level.txt
metalogger-1.0.1.dist-info/RECORD
